LICENSE
README.md
pyproject.toml
setup.py
combnet/__init__.py
combnet/core.py
combnet/functional.py
combnet/load.py
combnet/madmom.py
combnet/model.py
combnet/modules.py
combnet.egg-info/PKG-INFO
combnet.egg-info/SOURCES.txt
combnet.egg-info/dependency_links.txt
combnet.egg-info/requires.txt
combnet.egg-info/top_level.txt
combnet/assets/partitions/chords.json
combnet/assets/partitions/giantsteps.json
combnet/assets/partitions/giantsteps.old.json
combnet/assets/partitions/giantsteps_mtg.json
combnet/assets/partitions/giantsteps_mtg.old.json
combnet/assets/partitions/giantsteps_mtg_augment.json
combnet/assets/partitions/giantsteps_mtg_no_agument.json
combnet/assets/partitions/mdb.json
combnet/assets/partitions/notes.json
combnet/assets/partitions/ptdb.json
combnet/assets/partitions/timit.json
combnet/config/__init__.py
combnet/config/defaults.py
combnet/config/static.py
combnet/csrc/filters.cpp
combnet/data/__init__.py
combnet/data/collate.py
combnet/data/dataset.py
combnet/data/loader.py
combnet/data/statistics.py
combnet/data/augment/__init__.py
combnet/data/augment/__main__.py
combnet/data/augment/core.py
combnet/data/augment/pitch.py
combnet/data/download/__init__.py
combnet/data/download/__main__.py
combnet/data/download/core.py
combnet/data/download/timit.py
combnet/data/preprocess/__init__.py
combnet/data/preprocess/__main__.py
combnet/data/preprocess/core.py
combnet/data/preprocess/highpass_audio.py
combnet/data/preprocess/spectrogram.py
combnet/data/synthesize/__init__.py
combnet/data/synthesize/__main__.py
combnet/data/synthesize/chords.py
combnet/data/synthesize/core.py
combnet/data/synthesize/notes.py
combnet/evaluate/__init__.py
combnet/evaluate/__main__.py
combnet/evaluate/core.py
combnet/evaluate/metrics.py
combnet/filters/__init__.py
combnet/filters/basic.py
combnet/filters/multitap.py
combnet/filters/no_op.py
combnet/filters/lerp/__init__.py
combnet/filters/lerp/core.py
combnet/filters/lerp/triton/__init__.py
combnet/filters/lerp/triton/core.py
combnet/filters/lerp/triton/fused.py
combnet/filters/lerp/triton/tapered.py
combnet/filters/sinc/__init__.py
combnet/filters/sinc/triton/__init__.py
