Metadata-Version: 2.1
Name: combnet
Version: 1.0.1
Summary: Combolutional Neural Networks
Author-email: Cameron Churchwell <cameronchurchwell@icloud.com>
License: MIT License
Project-URL: Homepage, https://github.com/CameronChurchwell/combnet
Project-URL: Issues, https://github.com/CameronChurchwell/combnet/issues
Classifier: License :: OSI Approved :: MIT License
Requires-Python: >=3.8
License-File: LICENSE
Requires-Dist: GPUtil
Requires-Dist: numpy
Requires-Dist: torch
Requires-Dist: torchaudio
Requires-Dist: torchutil
Requires-Dist: yapecs
Requires-Dist: GPUtil
Requires-Dist: librosa
Requires-Dist: resampy
Requires-Dist: jax
Requires-Dist: pyfluidsynth
Requires-Dist: matplotlib
Requires-Dist: tqdm
Requires-Dist: pretty_midi
Requires-Dist: platformdirs
